ibuilder/__init__.py
ibuilder/__main__.py
ibuilder/history.py
ibuilder/images.py
ibuilder/main.py
ibuilder/models.py
ibuilder/utils.py
ibuilder/config/config.py
ibuilder/config/models.py
ibuilder-3.10.1.dist-info/METADATA
ibuilder-3.10.1.dist-info/WHEEL
ibuilder-3.10.1.dist-info/entry_points.txt
ibuilder-3.10.1.dist-info/licenses/LICENSE
ibuilder-3.10.1.dist-info/RECORD
