Metadata-Version: 2.4
Name: ibuilder
Version: 3.10.1
Summary: build, tag, and push docker images
Project-URL: Source, https://gitlab.com/drad/ibuilder
Project-URL: Documentation, https://gitlab.com/drad/ibuilder/-/wikis/home
Project-URL: Bug Tracker, https://gitlab.com/drad/ibuilder/-/issues
Author-email: drad <sa@adercon.com>
Maintainer-email: drad <sa@adercon.com>
License-Expression: GPL-3.0-only
License-File: LICENSE
Keywords: build,cd,ci,cli,containers,cosign,docker,git,image,push,sign,tag
Requires-Python: ~=3.11
Requires-Dist: arrow~=1.3
Requires-Dist: click~=8.1
Requires-Dist: docker~=7.1
Requires-Dist: packaging~=24.1
Requires-Dist: pydantic~=2.9
Requires-Dist: requests~=2.32
Requires-Dist: rich~=13.9
Requires-Dist: tinydb~=4.8
Requires-Dist: typer<0.13,>=0.12
